Workbook

Sheet Test Tracker
A1: Test Name | B1: Unit Test | C1: Integration Test | D1: API Test (Postman) | E1: Security Test | F1: UAT | G1: Regression Test | H1: Notes
A2: Auth
A3: Login (JWT issued correctly) | B3: TRUE | C3: TRUE | D3: FALSE | E3: FALSE | F3: FALSE | G3: FALSE | H3: LoginUserCommandHandlerTests; login drives every integration suite
A4: Registration / Invite user | B4: TRUE | C4: TRUE | D4: FALSE | E4: FALSE | F4: FALSE | G4: FALSE | H4: RegisterUserCommandHandlerTests; users registered across HR/Accounting integration
A5: Token refresh | B5: TRUE | C5: FALSE | D5: FALSE | E5: FALSE | F5: FALSE | G5: FALSE | H5: RefreshTokenCommandHandlerTests.RotatesTokens
A6: Token expiry enforcement | B6: TRUE | C6: FALSE | D6: FALSE | E6: FALSE | F6: FALSE | G6: FALSE | H6: RefreshTokenCommandHandlerTests.WithExpiredToken_ThrowsUnauthorized
A7: Logout / token revocation | B7: TRUE | C7: FALSE | D7: FALSE | E7: FALSE | F7: FALSE | G7: FALSE | H7: RefreshTokenCommandHandlerTests.WithRevokedToken revokes all sessions
A8: Role assignment (SuperAdmin/CompanyAdmin/Manager/Employee) | B8: TRUE | C8: FALSE | D8: FALSE | E8: FALSE | F8: FALSE | G8: FALSE | H8: RegisterUserCommandHandlerTests: cannot create equal/higher role; forced into own company
A9: Password hashing verification | B9: TRUE | C9: FALSE | D9: FALSE | E9: TRUE | F9: FALSE | G9: FALSE | H9: LoginUserCommandHandlerTests: wrong password rejected (hashed verify)
A10: Tenancy & Multi-Company
A11: Tenant registration (atomic: tenant + company + CEO) | B11: TRUE | C11: TRUE | D11: FALSE | E11: FALSE | F11: FALSE | G11: FALSE | H11: RegisterTenantCommandHandlerTests.Atomically; TenantIsolationTests signup
A12: Company create / list (SuperAdmin all, Admin own) | B12: TRUE | C12: FALSE | D12: FALSE | E12: FALSE | F12: FALSE | G12: FALSE | H12: CompanyAndBranchHandlerTests.ListCompanies_SuperAdmin_SeesAll_CompanyAdmin_SeesOwnOnly
A13: Cross-tenant data isolation (query filter, physical) | B13: TRUE | C13: TRUE | D13: FALSE | E13: TRUE | F13: FALSE | G13: FALSE | H13: TenantIsolationTests.TwoTenants_CanNeverSeeOrTouch; BranchQueryFilter_ConfinesUsersToTenant
A14: Duplicate email across tenants rejected | B14: TRUE | C14: TRUE | D14: FALSE | E14: FALSE | F14: FALSE | G14: FALSE | H14: RegisterTenant conflict; TenantIsolationTests.DuplicateEmailAcrossTenants
A15: HR
A16: Create employee | B16: TRUE | C16: TRUE | D16: FALSE | E16: FALSE | F16: FALSE | G16: FALSE | H16: EmployeeHandlerTests.Create_GeneratesEmployeeCode; HRModuleTests.PersonRegistry
A17: Update employee | B17: TRUE | C17: FALSE | D17: FALSE | E17: FALSE | F17: FALSE | G17: FALSE | H17: EmployeeHandlerTests.Update_ChangesEditableFields
A18: List employees (pagination + filter) | B18: TRUE | C18: TRUE | D18: FALSE | E18: FALSE | F18: FALSE | G18: FALSE | H18: EmployeeHandlerTests.List_ReturnsEmployees_WithPagingAndSearch; HRModuleTests
A19: Department CRUD | B19: FALSE | C19: TRUE | D19: FALSE | E19: FALSE | F19: FALSE | G19: FALSE | H19: HRModuleTests.SetupOrg creates department + designation
A20: Attendance check-in/out | B20: FALSE | C20: FALSE | D20: FALSE | E20: FALSE | F20: FALSE | G20: FALSE | H20: not in scope yet
A21: Leave request submission | B21: FALSE | C21: TRUE | D21: FALSE | E21: FALSE | F21: FALSE | G21: FALSE | H21: HRModuleTests.Leave_Apply_ConsumesBalance
A22: Leave approval — full multi-step flow | B22: FALSE | C22: FALSE | D22: FALSE | E22: FALSE | F22: FALSE | G22: FALSE | H22: approval engine proven separately; leave multi-step test pending
A23: Leave rejection — halts remaining steps | B23: FALSE | C23: FALSE | D23: FALSE | E23: FALSE | F23: FALSE | G23: FALSE | H23: approval reject proven (ApprovalEngineTests); leave-specific pending
A24: Salary field access restriction (Manager cannot view) | B24: TRUE | C24: FALSE | D24: FALSE | E24: TRUE | F24: FALSE | G24: FALSE | H24: EmployeeHandlerTests.Salary_IsVisibleToAdmin_ButHiddenFromManager
A25: Data isolation between companies (Employee) | B25: FALSE | C25: FALSE | D25: FALSE | E25: TRUE | F25: FALSE | G25: FALSE | H25: global CompanyEntity filter (BranchQueryFilter, TenantIsolationTests)
A26: Audit log entry created on employee update | B26: FALSE | C26: FALSE | D26: FALSE | E26: FALSE | F26: FALSE | G26: FALSE | H26: audit fields auto-set on save; assertion pending
A27: New-hire approval (202 -> approve -> employee created) | B27: FALSE | C27: TRUE | D27: FALSE | E27: FALSE | F27: FALSE | G27: FALSE | H27: HRModuleTests.CreateEmployee_TriggersApproval_WhenRuleExists
A28: Approvals
A29: Approval workflow config creation | B29: FALSE | C29: TRUE | D29: FALSE | E29: FALSE | F29: FALSE | G29: FALSE | H29: ApprovalEngineTests create rule; DuplicateActiveRule_IsForbidden
A30: Approval request created on submit | B30: FALSE | C30: TRUE | D30: FALSE | E30: FALSE | F30: FALSE | G30: FALSE | H30: ApprovalEngineTests.Submit_IsQueued_ThenApproval
A31: Sequential step progression (Step 1 → Step 2) | B31: FALSE | C31: FALSE | D31: FALSE | E31: FALSE | F31: FALSE | G31: FALSE | H31: single-approver flows tested; multi-step chain test pending
A32: Rejection at any step halts remaining steps | B32: FALSE | C32: TRUE | D32: FALSE | E32: FALSE | F32: FALSE | G32: FALSE | H32: ApprovalEngineTests.Reject_TerminatesRequest_AndDoesNotExecute
A33: Notification sent to correct approver | B33: FALSE | C33: FALSE | D33: FALSE | E33: FALSE | F33: FALSE | G33: FALSE | H33: no notifications feature yet
A34: Amount-threshold conditional step | B34: TRUE | C34: FALSE | D34: FALSE | E34: FALSE | F34: FALSE | G34: FALSE | H34: AmountThresholdTests (at/above queues, below runs, null always, resolvers)
A35: New module registers its transaction type automatically | B35: TRUE | C35: TRUE | D35: FALSE | E35: FALSE | F35: FALSE | G35: FALSE | H35: ApprovableActionsTests; accounting post gated in AccountingCycleTests
A36: Requester outranks approver -> auto-executes | B36: FALSE | C36: TRUE | D36: FALSE | E36: FALSE | F36: FALSE | G36: FALSE | H36: ApprovalEngineTests.RequesterOutranksApprover_AutoSkips
A37: Approved action that fails is recorded, not lost | B37: FALSE | C37: TRUE | D37: FALSE | E37: FALSE | F37: FALSE | G37: FALSE | H37: ApprovalEngineTests.ApprovedButExecutionFails_IsRecorded
A38: Accounting — Stage 1 (Foundation)
A39: Chart of Accounts — industry template seeding | B39: TRUE | C39: TRUE | D39: FALSE | E39: FALSE | F39: FALSE | G39: FALSE | H39: ChartOfAccountsTests.Seed_*; AccountingCycleTests seeds CoA over HTTP
A40: Chart of Accounts — custom edit (rename/add/deactivate) | B40: FALSE | C40: FALSE | D40: FALSE | E40: FALSE | F40: FALSE | G40: FALSE | H40: create/update/deactivate built; automated test pending
A41: Journal Entry creation (balanced) | B41: TRUE | C41: FALSE | D41: FALSE | E41: FALSE | F41: FALSE | G41: FALSE | H41: JournalPosterTests.Post_BalancedJournal_CreatesEntry
A42: Double-entry validation (rejects unbalanced entry) | B42: TRUE | C42: FALSE | D42: FALSE | E42: FALSE | F42: FALSE | G42: FALSE | H42: JournalPosterTests.Post_UnbalancedJournal_IsRejected; both debit+credit rejected
A43: Journal Entry posting | B43: TRUE | C43: TRUE | D43: FALSE | E43: FALSE | F43: FALSE | G43: FALSE | H43: JournalPosterTests; AccountingCycleTests posts the invoice journal
A44: Journal Entry void/reverse (no direct edit) | B44: TRUE | C44: FALSE | D44: FALSE | E44: FALSE | F44: FALSE | G44: FALSE | H44: JournalPosterTests.Void_PostsReversal; Void_AlreadyVoided_IsRejected
A45: Fiscal Year / Period setup | B45: TRUE | C45: FALSE | D45: FALSE | E45: FALSE | F45: FALSE | G45: FALSE | H45: FiscalCloseTests.CreateFiscalYear_Creates12Periods
A46: Period locking (cannot edit closed period) | B46: TRUE | C46: FALSE | D46: FALSE | E46: FALSE | F46: FALSE | G46: FALSE | H46: FiscalCloseTests.ClosedPeriod_BlocksPostingIntoIt
A47: Tax / VAT rate setup | B47: TRUE | C47: FALSE | D47: FALSE | E47: FALSE | F47: FALSE | G47: FALSE | H47: SeedTaxRates; VAT drives InvoicePosting/BillPosting recipes
A48: Data isolation between companies (Accounts/Journals) | B48: FALSE | C48: TRUE | D48: FALSE | E48: TRUE | F48: FALSE | G48: FALSE | H48: AccountingCycleTests.CeoConsolidation proves cross-tenant invisibility
A49: Accounting - Stage 2 (Sales & Purchases)
A50: Invoice - create draft + post (DR AR / CR Sales / CR VAT) | B50: TRUE | C50: TRUE | D50: FALSE | E50: FALSE | F50: FALSE | G50: FALSE | H50: InvoicePostingTests.Post_Invoice_ProducesExactRecipe; AccountingCycleTests
A51: Invoice - void (reversing journal, balance cleared) | B51: TRUE | C51: FALSE | D51: FALSE | E51: FALSE | F51: FALSE | G51: FALSE | H51: InvoicePostingTests.Void_PostedInvoice_ReversesJournal
A52: Invoice - posting approval-gated (202 -> approve -> journal) | B52: TRUE | C52: TRUE | D52: FALSE | E52: FALSE | F52: FALSE | G52: FALSE | H52: AccountingCycleTests.PostingInvoice_IsApprovalGated; ApprovableActionsTests
A53: Customer payment - allocation (full/partial; over-alloc rejected) | B53: TRUE | C53: TRUE | D53: FALSE | E53: FALSE | F53: FALSE | G53: FALSE | H53: CustomerPaymentTests (full/partial/over); AccountingCycleTests pays invoice
A54: Credit note - reverses revenue / VAT / receivable | B54: TRUE | C54: FALSE | D54: FALSE | E54: FALSE | F54: FALSE | G54: FALSE | H54: CreditNoteTests.CreditNote_ReversesRevenueVatAndReceivable
A55: Bill - post (DR Expense / DR VAT-Input / CR Payable) | B55: TRUE | C55: FALSE | D55: FALSE | E55: FALSE | F55: FALSE | G55: FALSE | H55: BillPostingTests.Post_Bill_ProducesExactRecipe
A56: Supplier payment - settles bill, reduces payable | B56: TRUE | C56: FALSE | D56: FALSE | E56: FALSE | F56: FALSE | G56: FALSE | H56: BillPostingTests.PaySupplier_SettlesBill_AndReducesPayable
A57: Debit note - reverses expense / VAT / payable | B57: TRUE | C57: FALSE | D57: FALSE | E57: FALSE | F57: FALSE | G57: FALSE | H57: DebitNoteTests.DebitNote_ReversesExpenseInputVatAndPayable
A58: Accounting - Stage 3 (Statements & Reporting)
A59: Trial Balance (from posted lines; debits = credits) | B59: TRUE | C59: FALSE | D59: FALSE | E59: FALSE | F59: FALSE | G59: FALSE | H59: JournalPosterTests.TrialBalance_AfterPosting_Balances
A60: Profit & Loss (revenue - expenses) | B60: TRUE | C60: TRUE | D60: FALSE | E60: FALSE | F60: FALSE | G60: FALSE | H60: StatementsTests.ProfitAndLoss_ShowsRevenue_AndNetProfit; AccountingCycleTests
A61: Balance Sheet (Assets = Liabilities + Equity + earnings) | B61: TRUE | C61: FALSE | D61: FALSE | E61: FALSE | F61: FALSE | G61: FALSE | H61: StatementsTests.BalanceSheet_Balances_WithCurrentYearEarnings
A62: Cash Flow (inflows / outflows / closing) | B62: TRUE | C62: FALSE | D62: FALSE | E62: FALSE | F62: FALSE | G62: FALSE | H62: CashFlowTests.CashFlow_ReportsInflowsOutflows_AndClosing
A63: VAT Return (output - input) | B63: TRUE | C63: FALSE | D63: FALSE | E63: FALSE | F63: FALSE | G63: FALSE | H63: BillPostingTests.VatReturn_NetsOutputMinusInput
A64: Multi-company consolidation (CEO - all companies) | B64: FALSE | C64: TRUE | D64: FALSE | E64: TRUE | F64: FALSE | G64: FALSE | H64: AccountingCycleTests.CeoConsolidation_SumsCompanies_AndNeverCrossesTenant
A65: General Ledger (per-account, running balance) | B65: FALSE | C65: FALSE | D65: FALSE | E65: FALSE | F65: FALSE | G65: FALSE | H65: built; automated test pending
A66: Aged AR/AP + Finance dashboard | B66: FALSE | C66: FALSE | D66: FALSE | E66: FALSE | F66: FALSE | G66: FALSE | H66: built; automated test pending
A67: Accounting - Stage 4 (Advanced & Compliance)
A68: Opening balances -> Retained Earnings | B68: TRUE | C68: FALSE | D68: FALSE | E68: FALSE | F68: FALSE | G68: FALSE | H68: OpeningBalancesTests.Post_SetsBalances_AndBalancesToRetainedEarnings
A69: Year-end close (P&L -> Retained Earnings, zeroes P&L) | B69: TRUE | C69: FALSE | D69: FALSE | E69: FALSE | F69: FALSE | G69: FALSE | H69: FiscalCloseTests.CloseYear_RollsNetProfitToRetainedEarnings
A70: Fixed assets - straight-line depreciation (monthly) | B70: TRUE | C70: FALSE | D70: FALSE | E70: FALSE | F70: FALSE | G70: FALSE | H70: DepreciationTests.RunDepreciation_PostsMonthlyStraightLine
A71: Bank reconciliation (reconciled vs ledger balance) | B71: TRUE | C71: FALSE | D71: FALSE | E71: FALSE | F71: FALSE | G71: FALSE | H71: BankReconciliationTests.Reconciliation_TracksReconciledVsLedgerBalance
A72: Payroll pay-run -> salary journal (via IJournalPoster) | B72: TRUE | C72: FALSE | D72: FALSE | E72: FALSE | F72: FALSE | G72: FALSE | H72: PayrollTests.PostPayRun_PostsSalaryJournal_ViaJournalPoster
A73: E-invoicing export (UBL 2.1 / PINT AE) | B73: TRUE | C73: FALSE | D73: FALSE | E73: FALSE | F73: FALSE | G73: FALSE | H73: EInvoiceExportTests.Export_ProducesValidUbl_WithPintAeAndCorrectTotals
A74: Multi-currency - foreign invoice/bill posts in base at rate | B74: TRUE | C74: FALSE | D74: FALSE | E74: FALSE | F74: FALSE | G74: FALSE | H74: MultiCurrencyTests.ForeignInvoice_PostsLedgerInBaseCurrency_AtResolvedRate
A75: Multi-currency - realized FX gain/loss on settlement | B75: TRUE | C75: FALSE | D75: FALSE | E75: FALSE | F75: FALSE | G75: FALSE | H75: MultiCurrencyTests customer/supplier FX gain and loss
A76: Unrealized FX revaluation (period-end, auto-reverses) | B76: TRUE | C76: FALSE | D76: FALSE | E76: FALSE | F76: FALSE | G76: FALSE | H76: MultiCurrencyTests.Revaluation_* (gain, loss, none, duplicate guard)
A77: Department-function access (Accounting-dept manager = accountant) | B77: TRUE | C77: FALSE | D77: FALSE | E77: TRUE | F77: FALSE | G77: FALSE | H77: AccountingAccessTests (accounting-dept manager has access; others do not)

Sheet Summary
A1: Module | B1: Test Count | C1: Unit % | D1: Integration % | E1: API (Postman) % | F1: Security % | G1: UAT % | H1: Regression % | I1: Overall Completion
A2: Auth | B2: 7 | C2: =COUNTIF('Test Tracker'!B3:B9,"TRUE")/COUNTA('Test Tracker'!B3:B9) -> 1 | D2: =COUNTIF('Test Tracker'!C3:C9,"TRUE")/COUNTA('Test Tracker'!C3:C9) -> 0.285714 | E2: =COUNTIF('Test Tracker'!D3:D9,"TRUE")/COUNTA('Test Tracker'!D3:D9) -> 0 | F2: =COUNTIF('Test Tracker'!E3:E9,"TRUE")/COUNTA('Test Tracker'!E3:E9) -> 0.142857 | G2: =COUNTIF('Test Tracker'!F3:F9,"TRUE")/COUNTA('Test Tracker'!F3:F9) -> 0 | H2: =COUNTIF('Test Tracker'!G3:G9,"TRUE")/COUNTA('Test Tracker'!G3:G9) -> 0 | I2: =COUNTIF('Test Tracker'!B3:G9,"TRUE")/((9-3+1)*6) -> 0.238095
A3: Tenancy & Multi-Company | B3: 4 | C3: =COUNTIF('Test Tracker'!B11:B14,"TRUE")/COUNTA('Test Tracker'!B11:B14) -> 1 | D3: =COUNTIF('Test Tracker'!C11:C14,"TRUE")/COUNTA('Test Tracker'!C11:C14) -> 0.75 | E3: =COUNTIF('Test Tracker'!D11:D14,"TRUE")/COUNTA('Test Tracker'!D11:D14) -> 0 | F3: =COUNTIF('Test Tracker'!E11:E14,"TRUE")/COUNTA('Test Tracker'!E11:E14) -> 0.25 | G3: =COUNTIF('Test Tracker'!F11:F14,"TRUE")/COUNTA('Test Tracker'!F11:F14) -> 0 | H3: =COUNTIF('Test Tracker'!G11:G14,"TRUE")/COUNTA('Test Tracker'!G11:G14) -> 0 | I3: =COUNTIF('Test Tracker'!B11:G14,"TRUE")/((14-11+1)*6) -> 0.333333
A4: HR | B4: 12 | C4: =COUNTIF('Test Tracker'!B16:B27,"TRUE")/COUNTA('Test Tracker'!B16:B27) -> 0.333333 | D4: =COUNTIF('Test Tracker'!C16:C27,"TRUE")/COUNTA('Test Tracker'!C16:C27) -> 0.416667 | E4: =COUNTIF('Test Tracker'!D16:D27,"TRUE")/COUNTA('Test Tracker'!D16:D27) -> 0 | F4: =COUNTIF('Test Tracker'!E16:E27,"TRUE")/COUNTA('Test Tracker'!E16:E27) -> 0.166667 | G4: =COUNTIF('Test Tracker'!F16:F27,"TRUE")/COUNTA('Test Tracker'!F16:F27) -> 0 | H4: =COUNTIF('Test Tracker'!G16:G27,"TRUE")/COUNTA('Test Tracker'!G16:G27) -> 0 | I4: =COUNTIF('Test Tracker'!B16:G27,"TRUE")/((27-16+1)*6) -> 0.152778
A5: Approvals | B5: 9 | C5: =COUNTIF('Test Tracker'!B29:B37,"TRUE")/COUNTA('Test Tracker'!B29:B37) -> 0.222222 | D5: =COUNTIF('Test Tracker'!C29:C37,"TRUE")/COUNTA('Test Tracker'!C29:C37) -> 0.666667 | E5: =COUNTIF('Test Tracker'!D29:D37,"TRUE")/COUNTA('Test Tracker'!D29:D37) -> 0 | F5: =COUNTIF('Test Tracker'!E29:E37,"TRUE")/COUNTA('Test Tracker'!E29:E37) -> 0 | G5: =COUNTIF('Test Tracker'!F29:F37,"TRUE")/COUNTA('Test Tracker'!F29:F37) -> 0 | H5: =COUNTIF('Test Tracker'!G29:G37,"TRUE")/COUNTA('Test Tracker'!G29:G37) -> 0 | I5: =COUNTIF('Test Tracker'!B29:G37,"TRUE")/((37-29+1)*6) -> 0.148148
A6: Accounting — Stage 1 (Foundation) | B6: 10 | C6: =COUNTIF('Test Tracker'!B39:B48,"TRUE")/COUNTA('Test Tracker'!B39:B48) -> 0.8 | D6: =COUNTIF('Test Tracker'!C39:C48,"TRUE")/COUNTA('Test Tracker'!C39:C48) -> 0.3 | E6: =COUNTIF('Test Tracker'!D39:D48,"TRUE")/COUNTA('Test Tracker'!D39:D48) -> 0 | F6: =COUNTIF('Test Tracker'!E39:E48,"TRUE")/COUNTA('Test Tracker'!E39:E48) -> 0.1 | G6: =COUNTIF('Test Tracker'!F39:F48,"TRUE")/COUNTA('Test Tracker'!F39:F48) -> 0 | H6: =COUNTIF('Test Tracker'!G39:G48,"TRUE")/COUNTA('Test Tracker'!G39:G48) -> 0 | I6: =COUNTIF('Test Tracker'!B39:G48,"TRUE")/((48-39+1)*6) -> 0.2
A7: Accounting - Stage 2 (Sales & Purchases) | B7: 8 | C7: =COUNTIF('Test Tracker'!B50:B57,"TRUE")/COUNTA('Test Tracker'!B50:B57) -> 1 | D7: =COUNTIF('Test Tracker'!C50:C57,"TRUE")/COUNTA('Test Tracker'!C50:C57) -> 0.375 | E7: =COUNTIF('Test Tracker'!D50:D57,"TRUE")/COUNTA('Test Tracker'!D50:D57) -> 0 | F7: =COUNTIF('Test Tracker'!E50:E57,"TRUE")/COUNTA('Test Tracker'!E50:E57) -> 0 | G7: =COUNTIF('Test Tracker'!F50:F57,"TRUE")/COUNTA('Test Tracker'!F50:F57) -> 0 | H7: =COUNTIF('Test Tracker'!G50:G57,"TRUE")/COUNTA('Test Tracker'!G50:G57) -> 0 | I7: =COUNTIF('Test Tracker'!B50:G57,"TRUE")/((57-50+1)*6) -> 0.229167
A8: Accounting - Stage 3 (Statements & Reporting) | B8: 8 | C8: =COUNTIF('Test Tracker'!B59:B66,"TRUE")/COUNTA('Test Tracker'!B59:B66) -> 0.625 | D8: =COUNTIF('Test Tracker'!C59:C66,"TRUE")/COUNTA('Test Tracker'!C59:C66) -> 0.25 | E8: =COUNTIF('Test Tracker'!D59:D66,"TRUE")/COUNTA('Test Tracker'!D59:D66) -> 0 | F8: =COUNTIF('Test Tracker'!E59:E66,"TRUE")/COUNTA('Test Tracker'!E59:E66) -> 0.125 | G8: =COUNTIF('Test Tracker'!F59:F66,"TRUE")/COUNTA('Test Tracker'!F59:F66) -> 0 | H8: =COUNTIF('Test Tracker'!G59:G66,"TRUE")/COUNTA('Test Tracker'!G59:G66) -> 0 | I8: =COUNTIF('Test Tracker'!B59:G66,"TRUE")/((66-59+1)*6) -> 0.166667
A9: Accounting - Stage 4 (Advanced & Compliance) | B9: 10 | C9: =COUNTIF('Test Tracker'!B68:B77,"TRUE")/COUNTA('Test Tracker'!B68:B77) -> 1 | D9: =COUNTIF('Test Tracker'!C68:C77,"TRUE")/COUNTA('Test Tracker'!C68:C77) -> 0 | E9: =COUNTIF('Test Tracker'!D68:D77,"TRUE")/COUNTA('Test Tracker'!D68:D77) -> 0 | F9: =COUNTIF('Test Tracker'!E68:E77,"TRUE")/COUNTA('Test Tracker'!E68:E77) -> 0.1 | G9: =COUNTIF('Test Tracker'!F68:F77,"TRUE")/COUNTA('Test Tracker'!F68:F77) -> 0 | H9: =COUNTIF('Test Tracker'!G68:G77,"TRUE")/COUNTA('Test Tracker'!G68:G77) -> 0 | I9: =COUNTIF('Test Tracker'!B68:G77,"TRUE")/((77-68+1)*6) -> 0.183333
A10: TOTAL PROJECT (all modules) | B10: 68 | C10: =(COUNTIF('Test Tracker'!B3:B9,"TRUE")+COUNTIF('Test Tracker'!B11:B14,"TRUE")+COUNTIF('Test Tracker'!B16:B27,"TRUE")+COUNTIF('Test Tracker'!B29:B37,"TRUE")+COUNTIF('Test Tracker'!B39:B48,"TRUE")+COUNTIF('Test Tracker'!B50:B57,"TRUE")+COUNTIF('Test Tracker'!B59:B66,"TRUE")+COUNTIF('Test Tracker'!B68:B77,"TRUE"))/(COUNTA('Test Tracker'!B3:B9)+COUNTA('Test Tracker'!B11:B14)+COUNTA('Test Tracker'!B16:B27)+COUNTA('Test Tracker'!B29:B37)+COUNTA('Test Tracker'!B39:B48)+COUNTA('Test Tracker'!B50:B57)+COUNTA('Test Tracker'!B59:B66)+COUNTA('Test Tracker'!B68:B77)) -> 0.705882 | D10: =(COUNTIF('Test Tracker'!C3:C9,"TRUE")+COUNTIF('Test Tracker'!C11:C14,"TRUE")+COUNTIF('Test Tracker'!C16:C27,"TRUE")+COUNTIF('Test Tracker'!C29:C37,"TRUE")+COUNTIF('Test Tracker'!C39:C48,"TRUE")+COUNTIF('Test Tracker'!C50:C57,"TRUE")+COUNTIF('Test Tracker'!C59:C66,"TRUE")+COUNTIF('Test Tracker'!C68:C77,"TRUE"))/(COUNTA('Test Tracker'!C3:C9)+COUNTA('Test Tracker'!C11:C14)+COUNTA('Test Tracker'!C16:C27)+COUNTA('Test Tracker'!C29:C37)+COUNTA('Test Tracker'!C39:C48)+COUNTA('Test Tracker'!C50:C57)+COUNTA('Test Tracker'!C59:C66)+COUNTA('Test Tracker'!C68:C77)) -> 0.352941 | E10: =(COUNTIF('Test Tracker'!D3:D9,"TRUE")+COUNTIF('Test Tracker'!D11:D14,"TRUE")+COUNTIF('Test Tracker'!D16:D27,"TRUE")+COUNTIF('Test Tracker'!D29:D37,"TRUE")+COUNTIF('Test Tracker'!D39:D48,"TRUE")+COUNTIF('Test Tracker'!D50:D57,"TRUE")+COUNTIF('Test Tracker'!D59:D66,"TRUE")+COUNTIF('Test Tracker'!D68:D77,"TRUE"))/(COUNTA('Test Tracker'!D3:D9)+COUNTA('Test Tracker'!D11:D14)+COUNTA('Test Tracker'!D16:D27)+COUNTA('Test Tracker'!D29:D37)+COUNTA('Test Tracker'!D39:D48)+COUNTA('Test Tracker'!D50:D57)+COUNTA('Test Tracker'!D59:D66)+COUNTA('Test Tracker'!D68:D77)) -> 0 | F10: =(COUNTIF('Test Tracker'!E3:E9,"TRUE")+COUNTIF('Test Tracker'!E11:E14,"TRUE")+COUNTIF('Test Tracker'!E16:E27,"TRUE")+COUNTIF('Test Tracker'!E29:E37,"TRUE")+COUNTIF('Test Tracker'!E39:E48,"TRUE")+COUNTIF('Test Tracker'!E50:E57,"TRUE")+COUNTIF('Test Tracker'!E59:E66,"TRUE")+COUNTIF('Test Tracker'!E68:E77,"TRUE"))/(COUNTA('Test Tracker'!E3:E9)+COUNTA('Test Tracker'!E11:E14)+COUNTA('Test Tracker'!E16:E27)+COUNTA('Test Tracker'!E29:E37)+COUNTA('Test Tracker'!E39:E48)+COUNTA('Test Tracker'!E50:E57)+COUNTA('Test Tracker'!E59:E66)+COUNTA('Test Tracker'!E68:E77)) -> 0.102941 | G10: =(COUNTIF('Test Tracker'!F3:F9,"TRUE")+COUNTIF('Test Tracker'!F11:F14,"TRUE")+COUNTIF('Test Tracker'!F16:F27,"TRUE")+COUNTIF('Test Tracker'!F29:F37,"TRUE")+COUNTIF('Test Tracker'!F39:F48,"TRUE")+COUNTIF('Test Tracker'!F50:F57,"TRUE")+COUNTIF('Test Tracker'!F59:F66,"TRUE")+COUNTIF('Test Tracker'!F68:F77,"TRUE"))/(COUNTA('Test Tracker'!F3:F9)+COUNTA('Test Tracker'!F11:F14)+COUNTA('Test Tracker'!F16:F27)+COUNTA('Test Tracker'!F29:F37)+COUNTA('Test Tracker'!F39:F48)+COUNTA('Test Tracker'!F50:F57)+COUNTA('Test Tracker'!F59:F66)+COUNTA('Test Tracker'!F68:F77)) -> 0 | H10: =(COUNTIF('Test Tracker'!G3:G9,"TRUE")+COUNTIF('Test Tracker'!G11:G14,"TRUE")+COUNTIF('Test Tracker'!G16:G27,"TRUE")+COUNTIF('Test Tracker'!G29:G37,"TRUE")+COUNTIF('Test Tracker'!G39:G48,"TRUE")+COUNTIF('Test Tracker'!G50:G57,"TRUE")+COUNTIF('Test Tracker'!G59:G66,"TRUE")+COUNTIF('Test Tracker'!G68:G77,"TRUE"))/(COUNTA('Test Tracker'!G3:G9)+COUNTA('Test Tracker'!G11:G14)+COUNTA('Test Tracker'!G16:G27)+COUNTA('Test Tracker'!G29:G37)+COUNTA('Test Tracker'!G39:G48)+COUNTA('Test Tracker'!G50:G57)+COUNTA('Test Tracker'!G59:G66)+COUNTA('Test Tracker'!G68:G77)) -> 0 | I10: =(COUNTIF('Test Tracker'!B3:G9,"TRUE")+COUNTIF('Test Tracker'!B11:G14,"TRUE")+COUNTIF('Test Tracker'!B16:G27,"TRUE")+COUNTIF('Test Tracker'!B29:G37,"TRUE")+COUNTIF('Test Tracker'!B39:G48,"TRUE")+COUNTIF('Test Tracker'!B50:G57,"TRUE")+COUNTIF('Test Tracker'!B59:G66,"TRUE")+COUNTIF('Test Tracker'!B68:G77,"TRUE"))/(((9-3+1)*6)+((14-11+1)*6)+((27-16+1)*6)+((37-29+1)*6)+((48-39+1)*6)+((57-50+1)*6)+((66-59+1)*6)+((77-68+1)*6)) -> 0.193627

Sheet How To Use
A1: How to use this test tracker
A3: - Each light-blue row is a Module header — a label only, no values entered on it.
A4: - The rows underneath it are the individual test cases inside that module.
A5: - For each test-type column (Unit / Integration / API / Security / UAT / Regression), pick TRUE or FALSE from the cell's dropdown.
A6: - TRUE = tested and passed. FALSE = not tested yet, or failed — update it as soon as the test is completed.
A7: - Green fills in automatically for TRUE, red for FALSE — for a quick visual scan of project status.
A8: - The Notes column (last column) is for any detail: reason for failure, bug number, or any comment.
A9: - The Summary sheet automatically calculates completion % per module and per test type, plus the total project % at the bottom — it updates itself from the Test Tracker sheet, no manual editing needed.
A11: Test types used (industry-standard categories):
A12: Unit Test - Tests a single piece of code (a function or class) in isolation.
A13: Integration Test - Tests multiple parts working together (e.g. service + database).
A14: API Test (Postman) - Tests API endpoints directly by sending real requests and checking the response.
... A17: Regression Test - Re-tests older features to confirm a new addition didn't break something that already worked.
